edx_arch_experiments/__init__.py
edx_arch_experiments/apps.py
edx_arch_experiments/models.py
edx_arch_experiments/config_watcher/__init__.py
edx_arch_experiments/config_watcher/apps.py
edx_arch_experiments/config_watcher/signals/__init__.py
edx_arch_experiments/config_watcher/signals/receivers.py
edx_arch_experiments/config_watcher/signals/tests/test_receivers.py
edx_arch_experiments/datadog_monitoring/__init__.py
edx_arch_experiments/datadog_monitoring/apps.py
edx_arch_experiments/datadog_monitoring/code_owner/__init__.py
edx_arch_experiments/datadog_monitoring/code_owner/datadog.py
edx_arch_experiments/datadog_monitoring/code_owner/utils.py
edx_arch_experiments/datadog_monitoring/scripts/datadog_search.py
edx_arch_experiments/datadog_monitoring/signals/handlers.py
edx_arch_experiments/datadog_monitoring/tests/__init__.py
edx_arch_experiments/datadog_monitoring/tests/test_apps.py
edx_arch_experiments/datadog_monitoring/tests/code_owner/__init__.py
edx_arch_experiments/datadog_monitoring/tests/code_owner/mock_views.py
edx_arch_experiments/datadog_monitoring/tests/code_owner/test_datadog.py
edx_arch_experiments/datadog_monitoring/tests/code_owner/test_utils.py
edx_arch_experiments/datadog_monitoring/tests/signals/test_handlers.py
edx_arch_experiments/migrations/0001_initial.py
edx_arch_experiments/migrations/__init__.py
edx_arch_experiments/scripts/generate_code_owner_mappings.py
edx_arch_experiments/scripts/get_action_errors.py
edx_arch_experiments/scripts/republish_failed_events.py
edx_arch_experiments/settings/__init__.py
edx_arch_experiments/settings/common.py
edx_arch_experiments/settings/production.py
edx_arch_experiments/settings/scripts.py
edx_arch_experiments/tests/test_stub.py
edx_arch_experiments-7.1.0.dist-info/licenses/LICENSE.txt
edx_arch_experiments-7.1.0.dist-info/METADATA
edx_arch_experiments-7.1.0.dist-info/WHEEL
edx_arch_experiments-7.1.0.dist-info/entry_points.txt
edx_arch_experiments-7.1.0.dist-info/top_level.txt
edx_arch_experiments-7.1.0.dist-info/RECORD
